uw_bookstore/VERSION
uw_bookstore/__init__.py
uw_bookstore/dao.py
uw_bookstore/digital_material.py
uw_bookstore/models.py
uw_bookstore/test.py
uw_bookstore/resources/book/file/uw/iacourse_status.json_regid_12345678901234567890123456789012
uw_bookstore/resources/book/file/uw/json_utf8_202507.ubs_quarter_autumn_sln1_10000_returnlink_t
uw_bookstore/resources/book/file/uw/json_utf8_202507.ubs_quarter_autumn_sln1_10001_returnlink_t
uw_bookstore/resources/book/file/uw/json_utf8_202507.ubs_quarter_autumn_sln1_19187_returnlink_t
uw_bookstore/resources/book/file/uw/json_utf8_202507.ubs_quarter_spring_sln1_13830_returnlink_t
uw_bookstore/resources/book/file/uw/json_utf8_202507.ubs_quarter_spring_sln1_13833_returnlink_t
uw_bookstore/tests/__init__.py
uw_bookstore/tests/test_digital_material.py
uw_bookstore/tests/test_textbook.py
uw_bookstore/util/__init__.py
uw_restclients_bookstore-1.4.2.dist-info/licenses/LICENSE
uw_restclients_bookstore-1.4.2.dist-info/METADATA
uw_restclients_bookstore-1.4.2.dist-info/WHEEL
uw_restclients_bookstore-1.4.2.dist-info/top_level.txt
uw_restclients_bookstore-1.4.2.dist-info/RECORD
